cellsystem/__init__.py
cellsystem/cellsystem.py
cellsystem/logging/__init__.py
cellsystem/logging/full.py
cellsystem/logging/geometric.py
cellsystem/logging/logged.py
cellsystem/logging/printer.py
cellsystem/logging/treelogs.py
cellsystem/logging/core/__init__.py
cellsystem/logging/core/log.py
cellsystem/logging/core/multi.py
cellsystem/logging/core/weak.py
cellsystem/simulation/__init__.py
cellsystem/simulation/action.py
cellsystem/simulation/cells.py
cellsystem/simulation/system.py
cellsystem/simulation/world.py
cellsystem/utils/__init__.py
cellsystem/utils/tree.py
cellsystem-0.4.2.dist-info/DESCRIPTION.rst
cellsystem-0.4.2.dist-info/METADATA
cellsystem-0.4.2.dist-info/RECORD
cellsystem-0.4.2.dist-info/WHEEL
cellsystem-0.4.2.dist-info/metadata.json
cellsystem-0.4.2.dist-info/top_level.txt
