Metadata-Version: 2.0
Name: cellsystem
Version: 0.4.2
Summary: An agent-based framework for the simulation of biological cell systems and more.
Home-page: https://github.com/Ad115/Cell-System
Author: Ad115
Author-email: a.garcia230395@gmail.com
License: UNKNOWN
Project-URL: Bug Reports, https://github.com/Ad115/Cell-System/issues
Project-URL: Say Thanks!, https://saythanks.io/to/Ad115
Project-URL: Source, https://github.com/Ad115/Cell-System/
Project-URL: Author, https://agargar.wordpress.com/
Keywords: simulation cell agents
Platform: UNKNOWN
Classifier: Development Status :: 3 - Alpha
Classifier: Intended Audience :: Science/Research
Classifier: Intended Audience :: Education
Classifier: Topic :: Scientific/Engineering :: Artificial Life
Classifier: Topic :: Scientific/Engineering :: Bio-Informatics
Classifier: Topic :: Scientific/Engineering :: Medical Science Apps.
Classifier: License :: OSI Approved :: MIT License
Classifier: Programming Language :: Python :: 3 :: Only
Provides-Extra: dev
Requires-Dist: ete3
Requires-Dist: matplotlib
Requires-Dist: numpy
Provides-Extra: dev
Requires-Dist: jupyter; extra == 'dev'
